acos_client/__init__.py
acos_client/client.py
acos_client/errors.py
acos_client/hash.py
acos_client/logutils.py
acos_client/multipart.py
acos_client/utils.py
acos_client/version.py
acos_client/tests/__init__.py
acos_client/tests/t.py
acos_client/tests/unit/__init__.py
acos_client/tests/unit/test_client.py
acos_client/tests/unit/test_hash.py
acos_client/tests/unit/test_logutils.py
acos_client/tests/unit/test_utils.py
acos_client/tests/unit/v21/__init__.py
acos_client/tests/unit/v21/test_high_availability.py
acos_client/tests/unit/v21/test_interfaces.py
acos_client/tests/unit/v21/test_partition.py
acos_client/tests/unit/v21/test_session.py
acos_client/tests/unit/v21/test_slb_health_monitor.py
acos_client/tests/unit/v21/test_slb_server.py
acos_client/tests/unit/v21/test_slb_service_group.py
acos_client/tests/unit/v21/test_slb_service_group_member.py
acos_client/tests/unit/v21/test_slb_template_cookie_persistence.py
acos_client/tests/unit/v21/test_slb_template_sourceip_persistence.py
acos_client/tests/unit/v21/test_slb_virtual_port.py
acos_client/tests/unit/v21/test_slb_virtual_server.py
acos_client/tests/unit/v21/test_system.py
acos_client/tests/unit/v30/__init__.py
acos_client/tests/unit/v30/test_bladeparam.py
acos_client/tests/unit/v30/test_dns.py
acos_client/tests/unit/v30/test_interface.py
acos_client/tests/unit/v30/test_license_manager.py
acos_client/tests/unit/v30/test_member.py
acos_client/tests/unit/v30/test_port.py
acos_client/tests/unit/v30/test_responses.py
acos_client/tests/unit/v30/test_sflow.py
acos_client/tests/unit/v30/test_slb_aflex.py
acos_client/tests/unit/v30/test_slb_common.py
acos_client/tests/unit/v30/test_slb_server.py
acos_client/tests/unit/v30/test_slb_service_group.py
acos_client/tests/unit/v30/test_slb_template_persistence.py
acos_client/tests/unit/v30/test_slb_virtual_port.py
acos_client/tests/unit/v30/test_slb_virtual_server.py
acos_client/tests/unit/v30/test_vlan.py
acos_client/tests/unit/v30/test_vrrpa.py
acos_client/v21/__init__.py
acos_client-2.10.0.dist-info/LICENSE
acos_client-2.10.0.dist-info/METADATA
acos_client-2.10.0.dist-info/WHEEL
acos_client-2.10.0.dist-info/top_level.txt
acos_client-2.10.0.dist-info/RECORD
