Metadata-Version: 2.1
Name: acos-client
Version: 2.10.0
Summary: A10 Networks ACOS API Client
Home-page: https://github.com/a10networks/acos-client
Author: A10 Networks
Author-email: opensource@a10networks.com
License: Apache
Keywords: a10 axapi acos adc slb load balancer
Platform: UNKNOWN
Classifier: Intended Audience :: Developers
Classifier: License :: OSI Approved :: Apache Software License
Classifier: Operating System :: MacOS :: MacOS X
Classifier: Operating System :: POSIX
Classifier: Programming Language :: Python
Classifier: Programming Language :: Python :: 2.6
Classifier: Programming Language :: Python :: 2.7
Classifier: Programming Language :: Python :: 3.3
Classifier: Programming Language :: Python :: 3.4
Classifier: Programming Language :: Python :: 3.5
Classifier: Programming Language :: Python :: 3.6
Classifier: Programming Language :: Python :: Implementation :: CPython
Classifier: Programming Language :: Python :: Implementation :: PyPy
Classifier: Topic :: Internet
Classifier: Topic :: Software Development :: Libraries :: Python Modules
Requires-Dist: requests (>=2.3.0)
Requires-Dist: six
Requires-Dist: uhashring
